my_math/__init__.py
my_math/unimore_math.py
unimore_cicd-0.2.dist-info/METADATA
unimore_cicd-0.2.dist-info/WHEEL
unimore_cicd-0.2.dist-info/top_level.txt
unimore_cicd-0.2.dist-info/RECORD
