Metadata-Version: 2.1
Name: unimore_cicd
Version: 0.2
Summary: A sample Python package to test CI/CD
Author: Angelo Ferrando
Author-email: angelo.ferrando42@gmail.com
Requires-Dist: pytest
